suhukonversi/__init__.py
suhukonversi-0.1.0.dist-info/METADATA
suhukonversi-0.1.0.dist-info/WHEEL
suhukonversi-0.1.0.dist-info/top_level.txt
suhukonversi-0.1.0.dist-info/RECORD
