Metadata-Version: 2.4
Name: suhukonversi
Version: 0.1.0
Summary: Library Python untuk konversi suhu antara Celsius, Fahrenheit, dan Kelvin
Author: Tikature
Author-email: detikaa10@gmail.com
Classifier: Programming Language :: Python :: 3
Classifier: License :: OSI Approved :: MIT License
Requires-Python: >=3.6
Dynamic: author
Dynamic: author-email
Dynamic: classifier
Dynamic: description
Dynamic: description-content-type
Dynamic: requires-python
Dynamic: summary
